LICENSE.txt
setup.py
multi_await/__init__.py
multi_await/helpers.py
multi_await.egg-info/PKG-INFO
multi_await.egg-info/SOURCES.txt
multi_await.egg-info/dependency_links.txt
multi_await.egg-info/requires.txt
multi_await.egg-info/top_level.txt