Metadata-Version: 2.1
Name: multi-await
Version: 1.0.2
Summary: A python package to wait for multiple awaitables
Home-page: https://github.com/hydrogen18/multi-await
Author: Eric Urban
Author-email: hydrogen18@gmail.com
License: UNKNOWN
Platform: UNKNOWN
Classifier: Programming Language :: Python :: 3
Classifier: License :: OSI Approved :: MIT License
Classifier: Operating System :: OS Independent
Requires-Python: >=3.7
License-File: LICENSE.txt
